MANIFEST.in
README.md
setup.py
chatglm_llm.egg-info/PKG-INFO
chatglm_llm.egg-info/SOURCES.txt
chatglm_llm.egg-info/dependency_links.txt
chatglm_llm.egg-info/entry_points.txt
chatglm_llm.egg-info/not-zip-safe
chatglm_llm.egg-info/requires.txt
chatglm_llm.egg-info/top_level.txt
chatglm_src/__init__.py
chatglm_src/cmd.py
chatglm_src/embeding.py
chatglm_src/serv.py
chatglm_src/chains/__init__.py
chatglm_src/chains/local_db.py
chatglm_src/chains/local_qa.py
chatglm_src/db/__init__.py
chatglm_src/db/local_res.py
chatglm_src/extention/__init__.py
chatglm_src/extention/cluster_and_smi.py
chatglm_src/extention/git.py
chatglm_src/extention/wrap_langchain/__init__.py
chatglm_src/extention/wrap_langchain/callbacks.py
chatglm_src/hf_server/__init__.py
chatglm_src/hf_server/cli_utils.py
chatglm_src/hf_server/llm_agent.py
chatglm_src/hf_server/models.py
chatglm_src/hf_server/utils.py
chatglm_src/loader/__init__.py
chatglm_src/models/__init__.py
chatglm_src/models/chatglm.py
chatglm_src/models/chatglm_utils.py
chatglm_src/models/hf.py
chatglm_src/models/normal.py
chatglm_src/models/qwen.py