Metadata-Version: 2.1
Name: chatglm-llm
Version: 1.7.7
Summary: chatglm llm
Home-page: https://github.com/xxx
Author: auth
Author-email: xxx@gmail.com
License: MIT
Platform: UNKNOWN
Provides-Extra: all
